command_builder/__init__.py
command_builder/command_builder.py
command_builder/py.typed
command_builder-0.1.3.dist-info/entry_points.txt
command_builder-0.1.3.dist-info/LICENSE
command_builder-0.1.3.dist-info/WHEEL
command_builder-0.1.3.dist-info/METADATA
command_builder-0.1.3.dist-info/RECORD
