Metadata-Version: 2.1
Name: command-builder
Version: 0.1.3
Summary: Summary shell commands execution
License: MIT
Author: Guilherme Righetto
Author-email: guilhermerighetto02@gmail.com
Requires-Python: >=3.6.2,<4.0.0
Classifier: License :: OSI Approved :: MIT License
Classifier: Programming Language :: Python :: 3
Classifier: Programming Language :: Python :: 3.7
Classifier: Programming Language :: Python :: 3.8
Classifier: Programming Language :: Python :: 3.9
